README.rst
setup.py
django_url_alias/__init__.py
django_url_alias/aliases.py
django_url_alias/models.py
django_url_alias/resolver.py
django_url_alias/settings.py
django_url_alias/urls.py
django_url_alias/utils.py
django_url_alias.egg-info/PKG-INFO
django_url_alias.egg-info/SOURCES.txt
django_url_alias.egg-info/dependency_links.txt
django_url_alias.egg-info/requires.txt
django_url_alias.egg-info/top_level.txt
django_url_alias/templatetags/__init__.py
django_url_alias/templatetags/url_alias.py