Metadata-Version: 1.1
Name: django-url-alias
Version: 0.2.0
Summary: Allow Django URLS to be completely rewritten (alias names for system URLs)
Home-page: https://github.com/ddanier/django_url_alias
Author: David Danier
Author-email: david.danier@team23.de
License: UNKNOWN
Platform: UNKNOWN
Classifier: Development Status :: 4 - Beta
Classifier: Environment :: Web Environment
Classifier: Framework :: Django
Classifier: Intended Audience :: Developers
Classifier: License :: OSI Approved :: BSD License
Classifier: Operating System :: OS Independent
Classifier: Programming Language :: Python
Classifier: Topic :: Utilities
